mars/__init__.py
mars/analysis/__init__.py
mars/analysis/config.py
mars/analysis/evaluator.py
mars/analysis/profiler.py
mars/analysis/report.py
mars/core/__init__.py
mars/core/base.py
mars/core/exceptions.py
mars/feature/__init__.py
mars/feature/binner.py
mars/feature/selector.py
mars/metrics/__init__.py
mars/metrics/calculation.py
mars/modeling/__init__.py
mars/modeling/base.py
mars/modeling/strategies.py
mars/modeling/tuner.py
mars/risk/__init__.py
mars/scoring/__init__.py
mars/utils/__init__.py
mars/utils/date.py
mars/utils/decorators.py
mars/utils/logger.py
mars/utils/plotter.py
mars_risk-0.0.7.dist-info/licenses/LICENSE
mars_risk-0.0.7.dist-info/METADATA
mars_risk-0.0.7.dist-info/WHEEL
mars_risk-0.0.7.dist-info/top_level.txt
mars_risk-0.0.7.dist-info/RECORD
