Metadata-Version: 2.4
Name: mars-risk
Version: 0.0.7
Summary: High-performance Risk Modeling Toolkit powered by Polars
Author-email: christian <lee_sq001@163.com>
License: MIT License
Keywords: risk,scorecard,polars,credit-scoring,feature-engineering
Requires-Python: >=3.10
License-File: LICENSE
Requires-Dist: polars>=1.0.0
Requires-Dist: numpy>=1.24.0
Requires-Dist: pandas>=2.0.0
Requires-Dist: pyarrow>=14.0.0
Requires-Dist: scikit-learn>=1.3.0
Requires-Dist: scipy>=1.10.0
Requires-Dist: optbinning>=0.19.0
Requires-Dist: joblib>=1.3.0
Requires-Dist: colorlog>=6.7.0
Provides-Extra: ml
Requires-Dist: xgboost>=2.0.0; extra == "ml"
Requires-Dist: lightgbm>=4.3.0; extra == "ml"
Requires-Dist: catboost>=1.2.0; extra == "ml"
Provides-Extra: dev
Requires-Dist: pytest>=7.4.0; extra == "dev"
Requires-Dist: black>=23.0.0; extra == "dev"
Requires-Dist: jupyterlab>=4.0.0; extra == "dev"
Requires-Dist: matplotlib>=3.7.0; extra == "dev"
Requires-Dist: seaborn>=0.12.0; extra == "dev"
Requires-Dist: tqdm>=4.66.0; extra == "dev"
Requires-Dist: psutil>=5.9.0; extra == "dev"
Dynamic: license-file
